Metadata-Version: 1.2
Name: kache
Version: 0.1.5
Summary: Persistent caching decorator
Home-page: http://github.com/egafni/Kache
Author: Erik Gafni
Author-email: egafni@gmail.com
Maintainer: Erik Gafni
Maintainer-email: egafni@gmail.com
License: MIT
Platform: UNKNOWN
Classifier: Programming Language :: Python :: 3
Classifier: Intended Audience :: Developers
Classifier: License :: OSI Approved :: MIT License
Classifier: Operating System :: MacOS
Classifier: Operating System :: Microsoft :: Windows
Classifier: Operating System :: POSIX
Classifier: Programming Language :: Python
Classifier: Topic :: Software Development
Classifier: Topic :: Utilities
